logproc.py
logproc-0.3.1.dist-info/licenses/LICENSE
logproc-0.3.1.dist-info/WHEEL
logproc-0.3.1.dist-info/METADATA
logproc-0.3.1.dist-info/RECORD
