Metadata-Version: 2.4
Name: logproc
Version: 0.3.1
Summary: Run a process and log stdin and stdout.
Author-email: Thorsten Vitt <tv@thorstenvitt.de>
Requires-Python: >=3.10
Classifier: License :: OSI Approved :: MIT License
License-File: LICENSE
Project-URL: repository, https://github.com/thvitt/logproc
